aiorest/security.py
aiorest/errors.py
aiorest/handler.py
aiorest/__init__.py
aiorest/server.py
aiorest/request.py
aiorest/session/redis_session.py
aiorest/session/interface.py
aiorest/session/base.py
aiorest/session/__init__.py
aiorest/session/cookie_session.py
aiorest-0.4.0.dist-info/DESCRIPTION.rst
aiorest-0.4.0.dist-info/WHEEL
aiorest-0.4.0.dist-info/METADATA
aiorest-0.4.0.dist-info/metadata.json
aiorest-0.4.0.dist-info/RECORD
aiorest-0.4.0.dist-info/top_level.txt
