Metadata-Version: 2.0
Name: aiorest
Version: 0.4.0
Summary: Support REST calls for asyncio+aiohttp.
Home-page: http://aiorest.readthedocs.org
Author: Andrew Svetlov
Author-email: andrew.svetlov@gmail.com
License: BSD
Download-URL: https://pypi.python.org/pypi/aiorest
Platform: OS Independent
Classifier: License :: OSI Approved :: BSD License
Classifier: Intended Audience :: Developers
Classifier: Programming Language :: Python
Classifier: Programming Language :: Python :: 3.3
Classifier: Programming Language :: Python :: 3.4
Classifier: Operating System :: OS Independent
Classifier: Environment :: Web Environment
Requires: aiohttp
Provides: aiorest
Requires-Dist: aiohttp (>=0.12)
Provides-Extra: redis_session
Requires-Dist: aioredis (>=0.1.3); extra == 'redis_session'
